oslo_config/__init__.py
oslo_config/_i18n.py
oslo_config/_list_opts.py
oslo_config/cfg.py
oslo_config/fixture.py
oslo_config/generator.py
oslo_config/iniparser.py
oslo_config/sphinxconfiggen.py
oslo_config/sphinxext.py
oslo_config/types.py
oslo_config/validator.py
oslo_config/version.py
oslo_config/sources/__init__.py
oslo_config/sources/_environment.py
oslo_config/sources/_uri.py
oslo_config/sources/templates/bash-completion.template
oslo_config/sources/templates/zsh-completion.template
oslo_config/tests/__init__.py
oslo_config/tests/test_cfg.py
oslo_config/tests/test_fixture.conf
oslo_config/tests/test_fixture.py
oslo_config/tests/test_generator.py
oslo_config/tests/test_get_location.py
oslo_config/tests/test_iniparser.py
oslo_config/tests/test_sources.py
oslo_config/tests/test_sphinxconfiggen.py
oslo_config/tests/test_sphinxext.py
oslo_config/tests/test_types.py
oslo_config/tests/test_validator.py
oslo_config/tests/testmods/__init__.py
oslo_config/tests/testmods/bar_foo_opt.py
oslo_config/tests/testmods/baz_qux_opt.py
oslo_config/tests/testmods/blaa_opt.py
oslo_config/tests/testmods/fbaar_baa_opt.py
oslo_config/tests/testmods/fbar_foo_opt.py
oslo_config/tests/testmods/fblaa_opt.py
oslo_config-10.2.0.dist-info/licenses/AUTHORS
oslo_config-10.2.0.dist-info/licenses/LICENSE
oslo_config-10.2.0.dist-info/METADATA
oslo_config-10.2.0.dist-info/WHEEL
oslo_config-10.2.0.dist-info/entry_points.txt
oslo_config-10.2.0.dist-info/pbr.json
oslo_config-10.2.0.dist-info/top_level.txt
oslo_config-10.2.0.dist-info/RECORD
