Metadata-Version: 2.4
Name: oslo.config
Version: 10.2.0
Summary: Oslo Configuration API
Author-email: OpenStack <openstack-discuss@lists.openstack.org>
License: Apache-2.0
Project-URL: Homepage, https://docs.openstack.org/oslo.config
Project-URL: Repository, https://opendev.org/openstack/oslo.config
Classifier: Development Status :: 5 - Production/Stable
Classifier: Environment :: OpenStack
Classifier: Intended Audience :: Developers
Classifier: Intended Audience :: Information Technology
Classifier: License :: OSI Approved :: Apache Software License
Classifier: Operating System :: OS Independent
Classifier: Programming Language :: Python
Classifier: Programming Language :: Python :: 3
Classifier: Programming Language :: Python :: 3.10
Classifier: Programming Language :: Python :: 3.11
Classifier: Programming Language :: Python :: 3.12
Classifier: Programming Language :: Python :: 3.13
Classifier: Programming Language :: Python :: 3 :: Only
Classifier: Programming Language :: Python :: Implementation :: CPython
Requires-Python: >=3.10
License-File: LICENSE
Requires-Dist: netaddr>=0.7.18
Requires-Dist: stevedore>=5.6.0
Requires-Dist: oslo.i18n>=3.15.3
Requires-Dist: rfc3986>=1.2.0
Requires-Dist: PyYAML>=5.1
Requires-Dist: requests>=2.18.0
Provides-Extra: rst-generator
Requires-Dist: rst2txt>=1.1.0; extra == "rst-generator"
Requires-Dist: sphinx>=1.8.0; extra == "rst-generator"
Dynamic: license-file
Dynamic: requires-dist
